AUTHORS.rst
CONTRIBUTING.rst
HISTORY.rst
LICENSE
MANIFEST.in
README.rst
requirements.txt
setup.py
epys/__init__.py
epys/classes.py
epys/draw.py
epys/events.py
epys/maps.py
epys/orbit.py
epys/read.py
epys/utils.py
epys.egg-info/PKG-INFO
epys.egg-info/SOURCES.txt
epys.egg-info/dependency_links.txt
epys.egg-info/not-zip-safe
epys.egg-info/pbr.json
epys.egg-info/requires.txt
epys.egg-info/top_level.txt
test/__init__.py
test/test_read.py