Metadata-Version: 1.0
Name: epys
Version: 0.3.5
Summary: A python library for handling EPS output.
Home-page: https://github.com/johnnycakes79/epys
Author: Jonathan McAuliffe
Author-email: watch.n.learn@gmail.com
License: BSD
Keywords: epys
Platform: UNKNOWN
